﻿﻿<menusettings>
<menu id='0' tabs='13' text='Home(?)' color='0xFFFFFFFF' />
</menusettings>
<tabsettings>
<tab id='0' parentid='0' text='Open DVD'>
<bkgvisual>0</bkgvisual>
<bkgindex>0</bkgindex>
<iconvisual>0</iconvisual>
<iconindex>0</iconindex>
<reflectvisual>0</reflectvisual>
<reflectindex>0</reflectindex>
<animstate>0</animstate>
<gradientstate>0</gradientstate>
<iconstate>0</iconstate>
<mtextcolor>0xA23A58FF</mtextcolor>
<rtextcolor>0xFFF1F1FF</rtextcolor>
</tab>
<tab id='1' parentid='0' text='Xbox 360 games'>
<bkgvisual>0</bkgvisual>
<bkgindex>0</bkgindex>
<iconvisual>0</iconvisual>
<iconindex>0</iconindex>
<reflectvisual>0</reflectvisual>
<reflectindex>0</reflectindex>
<animstate>0</animstate>
<gradientstate>0</gradientstate>
<iconstate>0</iconstate>
<mtextcolor>0xA23A58FF</mtextcolor>
<rtextcolor>0xFFF1F1FF</rtextcolor>
</tab>
<tab id='2' parentid='0' text='Xbox Live Arcade'>
<bkgvisual>0</bkgvisual>
<bkgindex>0</bkgindex>
<iconvisual>0</iconvisual>
<iconindex>0</iconindex>
<reflectvisual>0</reflectvisual>
<reflectindex>0</reflectindex>
<animstate>0</animstate>
<gradientstate>0</gradientstate>
<iconstate>0</iconstate>
<mtextcolor>0xA23A58FF</mtextcolor>
<rtextcolor>0xFFF1F1FF</rtextcolor>
</tab>
<tab id='3' parentid='0' text='Homebrew'>
<bkgvisual>0</bkgvisual>
<bkgindex>0</bkgindex>
<iconvisual>0</iconvisual>
<iconindex>0</iconindex>
<reflectvisual>0</reflectvisual>
<reflectindex>0</reflectindex>
<animstate>0</animstate>
<gradientstate>0</gradientstate>
<iconstate>0</iconstate>
<mtextcolor>0xA23A58FF</mtextcolor>
<rtextcolor>0xFFF1F1FF</rtextcolor>
</tab>
<tab id='4' parentid='0' text='Xbox Classic'>
<bkgvisual>0</bkgvisual>
<bkgindex>0</bkgindex>
<iconvisual>0</iconvisual>
<iconindex>0</iconindex>
<reflectvisual>0</reflectvisual>
<reflectindex>0</reflectindex>
<animstate>0</animstate>
<gradientstate>0</gradientstate>
<iconstate>0</iconstate>
<mtextcolor>0xA23A58FF</mtextcolor>
<rtextcolor>0xFFF1F1FF</rtextcolor>
</tab>
<tab id='5' parentid='0' text='Emulators'>
<bkgvisual>0</bkgvisual>
<bkgindex>0</bkgindex>
<iconvisual>0</iconvisual>
<iconindex>0</iconindex>
<reflectvisual>0</reflectvisual>
<reflectindex>0</reflectindex>
<animstate>0</animstate>
<gradientstate>0</gradientstate>
<iconstate>0</iconstate>
<mtextcolor>0xA23A58FF</mtextcolor>
<rtextcolor>0xFFF1F1FF</rtextcolor>
</tab>
<tab id='6' parentid='0' text='Section'>
<bkgvisual>0</bkgvisual>
<bkgindex>0</bkgindex>
<iconvisual>0</iconvisual>
<iconindex>0</iconindex>
<reflectvisual>0</reflectvisual>
<reflectindex>0</reflectindex>
<animstate>0</animstate>
<gradientstate>0</gradientstate>
<iconstate>0</iconstate>
<mtextcolor>0xA23A58FF</mtextcolor>
<rtextcolor>0xFFF1F1FF</rtextcolor>
</tab>
<tab id='7' parentid='0' text='Archives Manager'>
<bkgvisual>0</bkgvisual>
<bkgindex>0</bkgindex>
<iconvisual>0</iconvisual>
<iconindex>0</iconindex>
<reflectvisual>0</reflectvisual>
<reflectindex>0</reflectindex>
<animstate>0</animstate>
<gradientstate>0</gradientstate>
<iconstate>0</iconstate>
<mtextcolor>0xA23A58FF</mtextcolor>
<rtextcolor>0xFFF1F1FF</rtextcolor>
</tab>
<tab id='8' parentid='0' text='Copy Disc'>
<bkgvisual>0</bkgvisual>
<bkgindex>0</bkgindex>
<iconvisual>0</iconvisual>
<iconindex>0</iconindex>
<reflectvisual>0</reflectvisual>
<reflectindex>0</reflectindex>
<animstate>0</animstate>
<gradientstate>0</gradientstate>
<iconstate>0</iconstate>
<mtextcolor>0xA23A58FF</mtextcolor>
<rtextcolor>0xFFF1F1FF</rtextcolor>
</tab>
<tab id='9' parentid='0' text='Weather forecast'>
<bkgvisual>0</bkgvisual>
<bkgindex>0</bkgindex>
<iconvisual>0</iconvisual>
<iconindex>0</iconindex>
<reflectvisual>0</reflectvisual>
<reflectindex>0</reflectindex>
<animstate>0</animstate>
<gradientstate>0</gradientstate>
<iconstate>0</iconstate>
<mtextcolor>0xA23A58FF</mtextcolor>
<rtextcolor>0xFFF1F1FF</rtextcolor>
</tab>
<tab id='10' parentid='0' text='Configurations'>
<bkgvisual>0</bkgvisual>
<bkgindex>0</bkgindex>
<iconvisual>0</iconvisual>
<iconindex>0</iconindex>
<reflectvisual>0</reflectvisual>
<reflectindex>0</reflectindex>
<animstate>0</animstate>
<gradientstate>0</gradientstate>
<iconstate>0</iconstate>
<mtextcolor>0xA23A58FF</mtextcolor>
<rtextcolor>0xFFF1F1FF</rtextcolor>
</tab>
<tab id='11' parentid='0' text='Skins'>
<bkgvisual>0</bkgvisual>
<bkgindex>0</bkgindex>
<iconvisual>0</iconvisual>
<iconindex>0</iconindex>
<reflectvisual>0</reflectvisual>
<reflectindex>0</reflectindex>
<animstate>0</animstate>
<gradientstate>0</gradientstate>
<iconstate>0</iconstate>
<mtextcolor>0xA23A58FF</mtextcolor>
<rtextcolor>0xFFF1F1FF</rtextcolor>
</tab>
</tabsettings>
